ute_wrapper/__init__.py
ute_wrapper/constants.py
ute_wrapper/exceptions.py
ute_wrapper/models.py
ute_wrapper/ute.py
ute_wrapper-2.5.1.dist-info/LICENSE
ute_wrapper-2.5.1.dist-info/METADATA
ute_wrapper-2.5.1.dist-info/WHEEL
ute_wrapper-2.5.1.dist-info/RECORD
