Metadata-Version: 2.1
Name: ute-wrapper
Version: 2.5.1
Summary: [DEPRECATED] A wrapper to interact with UTE's API
Home-page: https://gitlab.com/rogs/ute/
License: GPL-3.0-or-later
Keywords: API,wrapper,UTE,Uruguay
Author: Roger Gonzalez
Author-email: roger@rogs.me
Requires-Python: >=3.9
Classifier: License :: OSI Approved :: GNU General Public License v3 or later (GPLv3+)
Classifier: Operating System :: OS Independent
Classifier: Programming Language :: Python :: 3
Classifier: Programming Language :: Python :: 3.9
Classifier: Programming Language :: Python :: 3.10
Classifier: Programming Language :: Python :: 3.11
Classifier: Programming Language :: Python :: 3.12
Requires-Dist: requests (>=2.0.0,<3.0.0)
Project-URL: Documentation, https://gitlab.com/rogs/ute/-/blob/master/README.md
Project-URL: Repository, https://gitlab.com/rogs/ute/
